[
  {
    "id": 65930,
    "name": "Aanjar",
    "state_id": 2287,
    "state_code": "BI",
    "country_id": 121,
    "country_code": "LB",
    "latitude": "33.72778000",
    "longitude": "35.93111000",
    "native": "عنجر",
    "timezone": "Asia/Beirut",
    "translations": {
      "br": "Aanjar",
      "ko": "안자르",
      "pt-BR": "Aanjar",
      "pt": "Aanjar",
      "nl": "Aanjar",
      "hr": "Aanjar",
      "fa": "عنجر",
      "de": "Aanjar",
      "es": "Aanjar",
      "fr": "Aanjar",
      "ja": "アーンジャル",
      "it": "Aanjar",
      "zh-CN": "安贾尔",
      "tr": "Aanjar",
      "ru": "Аанджар",
      "uk": "Анджар",
      "pl": "Aanjar",
      "hi": "अंजार",
      "ar": "عنجر"
    },
    "created_at": "2019-10-05T23:07:51",
    "updated_at": "2025-10-13T13:37:54",
    "flag": 1,
    "wikiDataId": "Q14842846"
  },
  {
    "id": 65931,
    "name": "Ain Ebel",
    "state_id": 2288,
    "state_code": "NA",
    "country_id": 121,
    "country_code": "LB",
    "latitude": "33.11023000",
    "longitude": "35.40251000",
    "native": "عين إبل",
    "timezone": "Asia/Beirut",
    "translations": {
      "br": "Ain Ebel",
      "ko": "아인 에벨",
      "pt-BR": "Ain Ebel",
      "pt": "Ain Ebel",
      "nl": "Ain Ebel",
      "hr": "Ain Ebel",
      "fa": "عین ایبل",
      "de": "Ain Ebel",
      "es": "Ain Ebel",
      "fr": "Aïn Ebel",
      "ja": "アイン・エベル",
      "it": "Ain Ebel",
      "zh-CN": "艾因埃贝尔",
      "tr": "Ayn Ebel",
      "ru": "Айн Эбель",
      "uk": "Айн-Ебель",
      "pl": "Ain Ebel",
      "hi": "ऐन एबेल",
      "ar": "عين إبل"
    },
    "created_at": "2019-10-05T23:07:51",
    "updated_at": "2025-10-13T13:37:54",
    "flag": 1,
    "wikiDataId": "Q2828135"
  },
  {
    "id": 65932,
    "name": "Baabda",
    "state_id": 2282,
    "state_code": "JL",
    "country_id": 121,
    "country_code": "LB",
    "latitude": "33.83389000",
    "longitude": "35.54417000",
    "native": "بعبدا",
    "timezone": "Asia/Beirut",
    "translations": {
      "br": "Baabda",
      "ko": "바브다",
      "pt-BR": "Baabda",
      "pt": "Baabda",
      "nl": "Baabda",
      "hr": "Baabda",
      "fa": "بعبدا",
      "de": "Baabda",
      "es": "Baabda",
      "fr": "Baabda",
      "ja": "バアブダ",
      "it": "Baabda",
      "zh-CN": "巴卜达",
      "tr": "Baabda",
      "ru": "Баабда",
      "uk": "Баабда",
      "pl": "Baabda",
      "hi": "बाब्दा",
      "ar": "بعبدا"
    },
    "created_at": "2019-10-05T23:07:51",
    "updated_at": "2025-10-13T13:37:54",
    "flag": 1,
    "wikiDataId": "Q26454"
  },
  {
    "id": 65933,
    "name": "Baalbek",
    "state_id": 2283,
    "state_code": "BH",
    "country_id": 121,
    "country_code": "LB",
    "latitude": "34.00583000",
    "longitude": "36.21806000",
    "native": "بعلبك",
    "timezone": "Asia/Beirut",
    "translations": {
      "br": "Baalbek",
      "ko": "바알베크",
      "pt-BR": "Baalbek",
      "pt": "Baalbek",
      "nl": "Baalbek",
      "hr": "Baalbek",
      "fa": "بعلبک",
      "de": "Baalbek",
      "es": "Baalbek",
      "fr": "Baalbek",
      "ja": "バールベック",
      "it": "Baalbek",
      "zh-CN": "巴勒贝克",
      "tr": "Baalbek",
      "ru": "Баальбек",
      "uk": "Баальбек",
      "pl": "Baalbek",
      "hi": "बाल्बेक",
      "ar": "بعلبك"
    },
    "created_at": "2019-10-05T23:07:51",
    "updated_at": "2025-10-13T13:37:54",
    "flag": 1,
    "wikiDataId": "Q178835"
  },
  {
    "id": 65934,
    "name": "Batroûn",
    "state_id": 2284,
    "state_code": "AS",
    "country_id": 121,
    "country_code": "LB",
    "latitude": "34.25528000",
    "longitude": "35.65806000",
    "native": "البترون",
    "timezone": "Asia/Beirut",
    "translations": {
      "br": "Batroûn",
      "ko": "바트룬",
      "pt-BR": "Batroûn",
      "pt": "Batroûn",
      "nl": "Batroûn",
      "hr": "Batroûn",
      "fa": "بترون",
      "de": "Batrun",
      "es": "Batroún",
      "fr": "Batroûn",
      "ja": "バトロン",
      "it": "Batroûn",
      "zh-CN": "巴特龙",
      "tr": "Batroûn",
      "ru": "Батрун",
      "uk": "Батрун",
      "pl": "Batroûn",
      "hi": "बैट्रोन",
      "ar": "البترون"
    },
    "created_at": "2019-10-05T23:07:51",
    "updated_at": "2025-10-13T13:37:54",
    "flag": 1,
    "wikiDataId": "Q3285145"
  },
  {
    "id": 65935,
    "name": "Bcharré",
    "state_id": 2284,
    "state_code": "AS",
    "country_id": 121,
    "country_code": "LB",
    "latitude": "34.25083000",
    "longitude": "36.01056000",
    "native": "بشري",
    "timezone": "Asia/Beirut",
    "translations": {
      "br": "Bcharré",
      "ko": "브샤레",
      "pt-BR": "Bcharré",
      "pt": "Bcharré",
      "nl": "Bcharré",
      "hr": "Bcharré",
      "fa": "بشار",
      "de": "Bcharré",
      "es": "Bcharré",
      "fr": "Bcharré",
      "ja": "ブシャレ",
      "it": "Bcharré",
      "zh-CN": "布沙雷",
      "tr": "Bcharré",
      "ru": "Бчарре",
      "uk": "Бішаре",
      "pl": "Bcharré",
      "hi": "बचार्रे",
      "ar": "بشري"
    },
    "created_at": "2019-10-05T23:07:51",
    "updated_at": "2025-10-13T13:37:54",
    "flag": 1,
    "wikiDataId": "Q181167"
  },
  {
    "id": 65936,
    "name": "Beirut",
    "state_id": 2286,
    "state_code": "BA",
    "country_id": 121,
    "country_code": "LB",
    "latitude": "33.89332000",
    "longitude": "35.50157000",
    "native": "بيروت",
    "timezone": "Asia/Beirut",
    "translations": {
      "br": "Beirout",
      "ko": "베이루트",
      "pt-BR": "Beirute",
      "pt": "Beirute",
      "nl": "Beiroet",
      "hr": "Bejrut",
      "fa": "بیروت",
      "de": "Beirut",
      "es": "Beirut",
      "fr": "Beyrouth",
      "ja": "ベイルート",
      "it": "Beirut",
      "zh-CN": "贝鲁特",
      "tr": "Beyrut",
      "ru": "Бейрут",
      "uk": "Бейрут",
      "pl": "Bejrut",
      "hi": "बेरूत",
      "ar": "بيروت"
    },
    "created_at": "2019-10-05T23:07:51",
    "updated_at": "2025-10-13T13:37:54",
    "flag": 1,
    "wikiDataId": "Q3820"
  },
  {
    "id": 65937,
    "name": "Bhamdoun",
    "state_id": 2282,
    "state_code": "JL",
    "country_id": 121,
    "country_code": "LB",
    "latitude": "33.79500000",
    "longitude": "35.65111000",
    "native": "بحمدون",
    "timezone": "Asia/Beirut",
    "translations": {
      "br": "Bhamdoun",
      "ko": "밤둔",
      "pt-BR": "Bhamdoun",
      "pt": "Bhamdoun",
      "nl": "Bhamdoun",
      "hr": "Bhamdoun",
      "fa": "بهمدون",
      "de": "Bhamdoun",
      "es": "Bhamdoun",
      "fr": "Bhamdoun",
      "ja": "バムドゥン",
      "it": "Bhamdoun",
      "zh-CN": "布汉顿",
      "tr": "Bhamdoun",
      "ru": "Бхамдун",
      "uk": "Бхамдун",
      "pl": "Bhamdoun",
      "hi": "भामदौन",
      "ar": "بحمدون"
    },
    "created_at": "2019-10-05T23:07:51",
    "updated_at": "2025-10-13T13:37:54",
    "flag": 1,
    "wikiDataId": "Q3820"
  },
  {
    "id": 65938,
    "name": "Bhamdoûn el Mhatta",
    "state_id": 2282,
    "state_code": "JL",
    "country_id": 121,
    "country_code": "LB",
    "latitude": "33.80861000",
    "longitude": "35.65972000",
    "native": "بحمدون المحطة",
    "timezone": "Asia/Beirut",
    "translations": {
      "br": "Bhamdoûn el Mhatta",
      "ko": "밤둔 엘 마타",
      "pt-BR": "Bhamdoûn el Mhatta",
      "pt": "Bhamdoûn el Mhatta",
      "nl": "Bhamdoûn el Mhatta",
      "hr": "Bhamdoûn el Mhatta",
      "fa": "بحمدون المحطه",
      "de": "Bhamdoûn el Mhatta",
      "es": "Bhamdoun el Mhatta",
      "fr": "Bhamdoûn el Mhatta",
      "ja": "バムドゥン・エル・マッタ",
      "it": "Bhamdoûn el Mhatta",
      "zh-CN": "巴姆顿·埃尔·马塔",
      "tr": "Bhamdoûn el Mhatta",
      "ru": "Bhamdoûn el Mhatta",
      "uk": "Бхамдун ель-Мхатта",
      "pl": "Bhamdoûn el Mhatta",
      "hi": "Bhamdoûn el Mhatta",
      "ar": "بحمدون المحطة"
    },
    "created_at": "2019-10-05T23:07:51",
    "updated_at": "2025-10-13T13:37:54",
    "flag": 1,
    "wikiDataId": "Q2900650"
  },
  {
    "id": 65939,
    "name": "Caza de Aakkar",
    "state_id": 2285,
    "state_code": "AK",
    "country_id": 121,
    "country_code": "LB",
    "latitude": "34.53333000",
    "longitude": "36.16667000",
    "native": "قضاء عكار",
    "timezone": "Asia/Beirut",
    "translations": {
      "br": "Caza de Aakkar",
      "ko": "카사 데 아카카르",
      "pt-BR": "Caza de Aakkar",
      "pt": "Caza de Aakkar",
      "nl": "Caza de Aakkar",
      "hr": "Kuća Aakkar",
      "fa": "کاخ آکار",
      "de": "Caza de Aakkar",
      "es": "Caza de Aakkar",
      "fr": "Chasse d'Aakkar",
      "ja": "カザ・デ・アッカル",
      "it": "Caza de Aakkar",
      "zh-CN": "阿卡之卡",
      "tr": "Aakkar Cezaevi",
      "ru": "Каза де Ааккар",
      "uk": "Будинок Ааккара",
      "pl": "Caza de Aakkar",
      "hi": "Caza de Aakkar",
      "ar": "قضاء عكار"
    },
    "created_at": "2019-10-05T23:07:51",
    "updated_at": "2025-10-13T13:37:54",
    "flag": 1,
    "wikiDataId": "Q419697"
  },
  {
    "id": 65940,
    "name": "Caza de Baabda",
    "state_id": 2282,
    "state_code": "JL",
    "country_id": 121,
    "country_code": "LB",
    "latitude": "33.84592000",
    "longitude": "35.66791000",
    "native": "قضاء بعبدا",
    "timezone": "Asia/Beirut",
    "translations": {
      "br": "Caza de Baabda",
      "ko": "카사 데 바브다",
      "pt-BR": "Caza de Baabda",
      "pt": "Caza de Baabda",
      "nl": "Caza de Baabda",
      "hr": "Kuća Baabda",
      "fa": "کاخ بعبدا",
      "de": "Caza de Baabda",
      "es": "Caza de Baabda",
      "fr": "Caza de Baabda",
      "ja": "カザ・デ・バアブダ",
      "it": "Caza de Baabda",
      "zh-CN": "巴卜达城堡",
      "tr": "Baabda Evi",
      "ru": "Каса де Баабда",
      "uk": "Будинок Баабди",
      "pl": "Caza de Baabda",
      "hi": "काज़ा डे बाब्दा",
      "ar": "قضاء بعبدا"
    },
    "created_at": "2019-10-05T23:07:51",
    "updated_at": "2025-10-13T13:37:54",
    "flag": 1,
    "wikiDataId": "Q211370"
  },
  {
    "id": 65941,
    "name": "Caza de Baalbek",
    "state_id": 2283,
    "state_code": "BH",
    "country_id": 121,
    "country_code": "LB",
    "latitude": "34.09822000",
    "longitude": "36.27157000",
    "native": "قضاء بعلبك",
    "timezone": "Asia/Beirut",
    "translations": {
      "br": "Kava Baalbek",
      "ko": "카사 데 발베크",
      "pt-BR": "Caza de Baalbek",
      "pt": "Caza de Baalbek",
      "nl": "Caza de Baalbek",
      "hr": "Kuća u Baalbeku",
      "fa": "کاخ بعلبک",
      "de": "Caza de Baalbek",
      "es": "Caza de Baalbek",
      "fr": "Caza de Baalbek",
      "ja": "バールベックの家",
      "it": "Caza de Baalbek",
      "zh-CN": "巴勒贝克城堡",
      "tr": "Baalbek Cezaevi",
      "ru": "Каза де Баальбек",
      "uk": "Будинок Баальбека",
      "pl": "Caza de Baalbek",
      "hi": "काज़ा डे बालबेक",
      "ar": "قضاء بعلبك"
    },
    "created_at": "2019-10-05T23:07:51",
    "updated_at": "2025-10-13T13:37:54",
    "flag": 1,
    "wikiDataId": "Q782804"
  },
  {
    "id": 65942,
    "name": "Caza de Bent Jbaïl",
    "state_id": 2288,
    "state_code": "NA",
    "country_id": 121,
    "country_code": "LB",
    "latitude": "33.15964000",
    "longitude": "35.41137000",
    "native": "قضاء بنت جبيل",
    "timezone": "Asia/Beirut",
    "translations": {
      "br": "Caza de Bent Jbaïl",
      "ko": "카자 드 벤트 주바일",
      "pt-BR": "Caza de Bent Jbaïl",
      "pt": "Caza de Bent Jbaïl",
      "nl": "Caza de Bent Jbaïl",
      "hr": "Kuća Bent Jbaïl",
      "fa": "کاخ بنت جبیل",
      "de": "Caza de Bent Jbaïl",
      "es": "Caza de Bent Jbaïl",
      "fr": "Caza de Bent Jbaïl",
      "ja": "カザ・デ・ベント・ジュバイル",
      "it": "Caza de Bent Jbaïl",
      "zh-CN": "卡扎德本特·朱拜尔",
      "tr": "Caza de Bent Jbaïl",
      "ru": "Caza de Bent Jbaïl",
      "uk": "Будинок Бент-Джбаїл",
      "pl": "Caza de Bent Jbaïl",
      "hi": "Caza de Bent Jbaïl",
      "ar": "قضاء بنت جبيل"
    },
    "created_at": "2019-10-05T23:07:51",
    "updated_at": "2025-10-13T13:37:54",
    "flag": 1,
    "wikiDataId": "Q145355"
  },
  {
    "id": 65943,
    "name": "Caza de Nabatîyé",
    "state_id": 2288,
    "state_code": "NA",
    "country_id": 121,
    "country_code": "LB",
    "latitude": "33.39435000",
    "longitude": "35.44483000",
    "native": "قضاء النبطية",
    "timezone": "Asia/Beirut",
    "translations": {
      "br": "Caza de Nabatîyé",
      "ko": "카사 드 나바티예",
      "pt-BR": "Caza de Nabatîyé",
      "pt": "Caza de Nabatîyé",
      "nl": "Caza de Nabatîyé",
      "hr": "Kuća Nabatîyéa",
      "fa": "کاخ نبطیه",
      "de": "Caza de Nabatîyé",
      "es": "Caza de Nabatîyé",
      "fr": "Caza de Nabatîyé",
      "ja": "カザ・デ・ナバティエ",
      "it": "Caza de Nabatîyé",
      "zh-CN": "纳巴蒂耶峡谷",
      "tr": "Caza de Nabatîyé",
      "ru": "Caza de Nabatîyé",
      "uk": "Будинок Набатії",
      "pl": "Caza de Nabatîyé",
      "hi": "Caza de Nabatîyé",
      "ar": "قضاء النبطية"
    },
    "created_at": "2019-10-05T23:07:51",
    "updated_at": "2025-10-13T13:37:54",
    "flag": 1,
    "wikiDataId": "Q680602"
  },
  {
    "id": 65944,
    "name": "En Nâqoûra",
    "state_id": 2281,
    "state_code": "JA",
    "country_id": 121,
    "country_code": "LB",
    "latitude": "33.11806000",
    "longitude": "35.13972000",
    "native": "En Nâqoûra",
    "timezone": "Asia/Beirut",
    "translations": {
      "br": "En Nâqoûra",
      "ko": "엔 나쿠라",
      "pt-BR": "En Nâqoûra",
      "pt": "En Nâqoûra",
      "nl": "En Nâqoûra",
      "hr": "En Naqoûra",
      "fa": "در ناقوره",
      "de": "En Nâqoûra",
      "es": "En Nâqoûra",
      "fr": "En Nâqoûra",
      "ja": "エン・ナクーラ",
      "it": "En Nâqoûra",
      "zh-CN": "恩纳库拉",
      "tr": "En Nâqoûra",
      "ru": "En Nâqoûra",
      "uk": "Ен Накура",
      "pl": "En Nâqoûra",
      "hi": "En Nâqoûra",
      "ar": "En Nâqoûra"
    },
    "created_at": "2019-10-05T23:07:51",
    "updated_at": "2025-10-13T13:37:54",
    "flag": 1,
    "wikiDataId": "Q748504"
  },
  {
    "id": 65945,
    "name": "Ghazieh",
    "state_id": 2281,
    "state_code": "JA",
    "country_id": 121,
    "country_code": "LB",
    "latitude": "33.51750000",
    "longitude": "35.36889000",
    "native": "غازية",
    "timezone": "Asia/Beirut",
    "translations": {
      "br": "Ghazieh",
      "ko": "가지에",
      "pt-BR": "Ghazieh",
      "pt": "Ghazieh",
      "nl": "Ghazieh",
      "hr": "Ghazieh",
      "fa": "غازیه",
      "de": "Ghazieh",
      "es": "Ghazieh",
      "fr": "Ghazieh",
      "ja": "ガジエ",
      "it": "Ghazieh",
      "zh-CN": "加齐耶",
      "tr": "Gazieh",
      "ru": "Газие",
      "uk": "Газія",
      "pl": "Ghazieh",
      "hi": "गाज़ीह",
      "ar": "غازية"
    },
    "created_at": "2019-10-05T23:07:51",
    "updated_at": "2025-10-13T13:37:54",
    "flag": 1,
    "wikiDataId": "Q748504"
  },
  {
    "id": 65946,
    "name": "Habboûch",
    "state_id": 2288,
    "state_code": "NA",
    "country_id": 121,
    "country_code": "LB",
    "latitude": "33.40729000",
    "longitude": "35.48169000",
    "native": "حبوش",
    "timezone": "Asia/Beirut",
    "translations": {
      "br": "Habboûch",
      "ko": "하부흐",
      "pt-BR": "Habboûch",
      "pt": "Habboûch",
      "nl": "Habboûch",
      "hr": "Habbouch",
      "fa": "هابوچ",
      "de": "Habboûch",
      "es": "Habbouch",
      "fr": "Habboûch",
      "ja": "ハブブーシュ",
      "it": "Habboûch",
      "zh-CN": "哈布什",
      "tr": "Habboûch",
      "ru": "Хаббух",
      "uk": "Хаббух",
      "pl": "Habboûch",
      "hi": "हब्बूच",
      "ar": "حبوش"
    },
    "created_at": "2019-10-05T23:07:51",
    "updated_at": "2025-10-13T13:37:54",
    "flag": 1,
    "wikiDataId": "Q748504"
  },
  {
    "id": 65947,
    "name": "Jbaïl",
    "state_id": 2282,
    "state_code": "JL",
    "country_id": 121,
    "country_code": "LB",
    "latitude": "34.12111000",
    "longitude": "35.64806000",
    "native": "جبيل",
    "timezone": "Asia/Beirut",
    "translations": {
      "br": "Jbail",
      "ko": "자바일",
      "pt-BR": "Jbaïl",
      "pt": "Jbaïl",
      "nl": "Jbaïl",
      "hr": "Jbaïl",
      "fa": "جبیل",
      "de": "Dbaïl",
      "es": "Jbail",
      "fr": "Jbaïl",
      "ja": "ジュバイル",
      "it": "Jbaïl",
      "zh-CN": "朱拜勒",
      "tr": "Jbaïl",
      "ru": "Джабаиль",
      "uk": "Джбаїл",
      "pl": "Dżbail",
      "hi": "जबाइल",
      "ar": "جبيل"
    },
    "created_at": "2019-10-05T23:07:51",
    "updated_at": "2025-10-13T13:37:54",
    "flag": 1,
    "wikiDataId": "Q173532"
  },
  {
    "id": 65948,
    "name": "Jounieh",
    "state_id": 2282,
    "state_code": "JL",
    "country_id": 121,
    "country_code": "LB",
    "latitude": "33.98083000",
    "longitude": "35.61778000",
    "native": "جونيه",
    "timezone": "Asia/Beirut",
    "translations": {
      "br": "Jounieh",
      "ko": "주니에",
      "pt-BR": "Jounieh",
      "pt": "Jounieh",
      "nl": "Jounieh",
      "hr": "Džunije",
      "fa": "جونیه",
      "de": "Jounieh",
      "es": "Jounieh",
      "fr": "Jounieh",
      "ja": "ジュニエ",
      "it": "Jounieh",
      "zh-CN": "朱尼耶",
      "tr": "Jounieh",
      "ru": "Джуния",
      "uk": "Джуніє",
      "pl": "Dżunija",
      "hi": "जौनीह",
      "ar": "جونيه"
    },
    "created_at": "2019-10-05T23:07:51",
    "updated_at": "2025-10-13T13:37:54",
    "flag": 1,
    "wikiDataId": "Q173532"
  },
  {
    "id": 65949,
    "name": "Marjayoûn",
    "state_id": 2288,
    "state_code": "NA",
    "country_id": 121,
    "country_code": "LB",
    "latitude": "33.36028000",
    "longitude": "35.59111000",
    "native": "مرجعيون",
    "timezone": "Asia/Beirut",
    "translations": {
      "br": "Marjayoûn",
      "ko": "마르자윤",
      "pt-BR": "Marjayoûn",
      "pt": "Marjayoûn",
      "nl": "Marjayoûn",
      "hr": "Marjayoûn",
      "fa": "مرجعیون",
      "de": "Marjayoûn",
      "es": "Marjayoûn",
      "fr": "Marjayoûn",
      "ja": "マルジャユン",
      "it": "Marjayoûn",
      "zh-CN": "马尔贾永",
      "tr": "Marjayoun",
      "ru": "Марджаюн",
      "uk": "Марджаюн",
      "pl": "Marjayoun",
      "hi": "मार्जायोन",
      "ar": "مرجعيون"
    },
    "created_at": "2019-10-05T23:07:51",
    "updated_at": "2025-10-13T13:37:54",
    "flag": 1,
    "wikiDataId": "Q25659"
  },
  {
    "id": 65950,
    "name": "Nabatîyé et Tahta",
    "state_id": 2288,
    "state_code": "NA",
    "country_id": 121,
    "country_code": "LB",
    "latitude": "33.37889000",
    "longitude": "35.48389000",
    "native": "Nabatîyé et Tahta",
    "timezone": "Asia/Beirut",
    "translations": {
      "br": "Nabatîyé et Tahta",
      "ko": "나바티예 에 타타",
      "pt-BR": "Nabatîyé e Tahta",
      "pt": "Nabatîyé e Tahta",
      "nl": "Nabatîyé et Tahta",
      "hr": "Nabatiyé i Tahta",
      "fa": "نبطیه و تهتا",
      "de": "Nabatîyé et Tahta",
      "es": "Nabatîyé et Tahta",
      "fr": "Nabatîyé et Tahta",
      "ja": "ナバティエ・エト・タフタ",
      "it": "Nabatîyé et Tahta",
      "zh-CN": "纳巴蒂耶和塔赫塔",
      "tr": "Nabatîyé et Tahta",
      "ru": "Nabatîyé et Tahta",
      "uk": "Набатії та Тахта",
      "pl": "Nabatîyé et Tahta",
      "hi": "नबातिये एट ताहता",
      "ar": "Nabatîyé et Tahta"
    },
    "created_at": "2019-10-05T23:07:51",
    "updated_at": "2025-10-13T13:37:54",
    "flag": 1,
    "wikiDataId": "Q26134"
  },
  {
    "id": 65951,
    "name": "Ra’s Bayrūt",
    "state_id": 2286,
    "state_code": "BA",
    "country_id": 121,
    "country_code": "LB",
    "latitude": "33.90000000",
    "longitude": "35.48333000",
    "native": "رأس بيروت",
    "timezone": "Asia/Beirut",
    "translations": {
      "br": "Ra's Bayrūt",
      "ko": "라스 바이루트",
      "pt-BR": "Ra's Bayrūt",
      "pt": "Ra's Bayrūt",
      "nl": "Ra's Bayrūt",
      "hr": "Ra's Bayrūt",
      "fa": "رأس بیروت",
      "de": "Ra’s Bayrūt",
      "es": "Bayrūt de Ra",
      "fr": "Ra's Bayrūt",
      "ja": "ラーのバイルート",
      "it": "Ra’s Bayrūt",
      "zh-CN": "拉斯·巴伊鲁特",
      "tr": "Ra's Bayrūt",
      "ru": "Ра’с Байрут",
      "uk": "Ра'с Байрут",
      "pl": "Ra’s Bayrūt",
      "hi": "रा का बैरूत",
      "ar": "رأس بيروت"
    },
    "created_at": "2019-10-05T23:07:51",
    "updated_at": "2025-10-13T13:37:54",
    "flag": 1,
    "wikiDataId": "Q26134"
  },
  {
    "id": 65952,
    "name": "Sidon",
    "state_id": 2281,
    "state_code": "JA",
    "country_id": 121,
    "country_code": "LB",
    "latitude": "33.55751000",
    "longitude": "35.37148000",
    "native": "صيدا",
    "timezone": "Asia/Beirut",
    "translations": {
      "br": "Sidon",
      "ko": "시돈",
      "pt-BR": "Sidon",
      "pt": "Sidon",
      "nl": "Sidon",
      "hr": "Sidon",
      "fa": "صیدون",
      "de": "Sidon",
      "es": "Sidón",
      "fr": "Sidon",
      "ja": "シドン",
      "it": "Sidone",
      "zh-CN": "西顿",
      "tr": "Sayda",
      "ru": "Сидон",
      "uk": "Сидон",
      "pl": "Sydon",
      "hi": "सीदोन",
      "ar": "صيدا"
    },
    "created_at": "2019-10-05T23:07:51",
    "updated_at": "2025-10-13T13:37:54",
    "flag": 1,
    "wikiDataId": "Q163490"
  },
  {
    "id": 65953,
    "name": "Tripoli",
    "state_id": 2284,
    "state_code": "AS",
    "country_id": 121,
    "country_code": "LB",
    "latitude": "34.43352000",
    "longitude": "35.84415000",
    "native": "طرابلس",
    "timezone": "Asia/Beirut",
    "translations": {
      "br": "Tripoli",
      "ko": "트리폴리",
      "pt-BR": "Trípoli",
      "pt": "Trípoli",
      "nl": "Tripoli",
      "hr": "Tripoli",
      "fa": "طرابلس",
      "de": "Tripolis",
      "es": "Trípoli",
      "fr": "Tripoli",
      "ja": "トリポリ",
      "it": "Tripoli",
      "zh-CN": "硅藻土",
      "tr": "Trablus",
      "ru": "Триполи",
      "uk": "Триполі",
      "pl": "Trypolis",
      "hi": "त्रिपोली",
      "ar": "طرابلس"
    },
    "created_at": "2019-10-05T23:07:51",
    "updated_at": "2025-10-13T13:37:54",
    "flag": 1,
    "wikiDataId": "Q168954"
  },
  {
    "id": 65954,
    "name": "Tyre",
    "state_id": 2281,
    "state_code": "JA",
    "country_id": 121,
    "country_code": "LB",
    "latitude": "33.27333000",
    "longitude": "35.19389000",
    "native": "إطار",
    "timezone": "Asia/Beirut",
    "translations": {
      "br": "Bandenn-rod",
      "ko": "타이어",
      "pt-BR": "Pneu",
      "pt": "Pneu",
      "nl": "Band",
      "hr": "Guma",
      "fa": "تایر",
      "de": "Reifen",
      "es": "Neumático",
      "fr": "Pneu",
      "ja": "タイヤ",
      "it": "Pneumatico",
      "zh-CN": "胎",
      "tr": "Yorulmak",
      "ru": "Шина",
      "uk": "Тир",
      "pl": "Opona",
      "hi": "थका देना",
      "ar": "إطار"
    },
    "created_at": "2019-10-05T23:07:51",
    "updated_at": "2025-10-13T13:37:54",
    "flag": 1,
    "wikiDataId": "Q82070"
  },
  {
    "id": 65955,
    "name": "Zahlé",
    "state_id": 2287,
    "state_code": "BI",
    "country_id": 121,
    "country_code": "LB",
    "latitude": "33.84675000",
    "longitude": "35.90203000",
    "native": "زحلة",
    "timezone": "Asia/Beirut",
    "translations": {
      "br": "Zahlé",
      "ko": "자흘레",
      "pt-BR": "Zahlé",
      "pt": "Zahlé",
      "nl": "Zahlé",
      "hr": "Zahlé",
      "fa": "زحله",
      "de": "Zahlé",
      "es": "Zahlé",
      "fr": "Zahlé",
      "ja": "ザレ",
      "it": "Zahlé",
      "zh-CN": "扎赫勒",
      "tr": "Zahlé",
      "ru": "Захле",
      "uk": "Захле",
      "pl": "Zahlé",
      "hi": "Zahle",
      "ar": "زحلة"
    },
    "created_at": "2019-10-05T23:07:51",
    "updated_at": "2025-10-13T13:37:54",
    "flag": 1,
    "wikiDataId": "Q26569"
  }
]