[
  {
    "id": 154980,
    "name": "Fort-de-France",
    "state_id": 5398,
    "state_code": "01",
    "country_id": 138,
    "country_code": "MQ",
    "latitude": "14.64924180",
    "longitude": "-61.10984450",
    "native": "Fort-de-France",
    "timezone": "America/Caracas",
    "translations": {
      "br": "Kreñvlec'h Bro-C'hall",
      "ko": "포르드프랑스",
      "pt-BR": "Forte-de-França",
      "pt": "Forte-de-França",
      "nl": "Fort-de-France",
      "hr": "Fort-de-France",
      "fa": "فورت-دو-فرانس",
      "de": "Fort-de-France",
      "es": "Fort-de-France",
      "fr": "Fort-de-France",
      "ja": "フォール・ド・フランス",
      "it": "Fort-de-France",
      "zh-CN": "法兰西堡",
      "tr": "Fort-de-France",
      "ru": "Фор-де-Франс",
      "uk": "Форт-де-Франс",
      "pl": "Fort-de-France",
      "hi": "फोर्ट-डे-फ्रांस",
      "ar": "فورت دو فرانس"
    },
    "created_at": "2025-03-29T15:49:53",
    "updated_at": "2025-10-13T13:38:21",
    "flag": 1,
    "wikiDataId": "Q81621"
  },
  {
    "id": 154981,
    "name": "Le Lamentin",
    "state_id": 5398,
    "state_code": "01",
    "country_id": 138,
    "country_code": "MQ",
    "latitude": "14.62308620",
    "longitude": "-61.03347490",
    "native": "Le Lamentin",
    "timezone": "America/Caracas",
    "translations": {
      "br": "Le Lamentin",
      "ko": "르 라멘틴",
      "pt-BR": "O Lamentin",
      "pt": "O Lamentin",
      "nl": "Le Lamentin",
      "hr": "Le Lamentin",
      "fa": "لو لامنتن",
      "de": "Le Lamentin",
      "es": "El Lamentin",
      "fr": "Le Lamentin",
      "ja": "ル・ラメンタン",
      "it": "Le Lamentin",
      "zh-CN": "拉芒坦",
      "tr": "Le Lamentin",
      "ru": "Ле Ламантен",
      "uk": "Ле Ламентен",
      "pl": "Lamentin",
      "hi": "ले लामेंटिन",
      "ar": "لو لامنتين"
    },
    "created_at": "2025-03-29T15:49:53",
    "updated_at": "2025-10-13T13:38:21",
    "flag": 1,
    "wikiDataId": "Q947069"
  },
  {
    "id": 154982,
    "name": "Saint-Joseph",
    "state_id": 5398,
    "state_code": "01",
    "country_id": 138,
    "country_code": "MQ",
    "latitude": "14.68353400",
    "longitude": "-61.08186620",
    "native": "Saint-joseph",
    "timezone": "America/Caracas",
    "translations": {
      "br": "Sant-Jozef",
      "ko": "성 요셉",
      "pt-BR": "São José",
      "pt": "São José",
      "nl": "Sint-Jozef",
      "hr": "Sveti Josip",
      "fa": "سنت جوزف",
      "de": "Saint-Joseph",
      "es": "San José",
      "fr": "Saint-Joseph",
      "ja": "聖ヨセフ",
      "it": "San Giuseppe",
      "zh-CN": "圣约瑟夫",
      "tr": "Aziz Joseph",
      "ru": "Сен-Жозеф",
      "uk": "Сен-Жозеф",
      "pl": "Święty Józef",
      "hi": "सेंट जोसेफ",
      "ar": "القديس يوسف"
    },
    "created_at": "2025-03-29T15:49:53",
    "updated_at": "2025-10-13T13:38:21",
    "flag": 1,
    "wikiDataId": "Q918737"
  },
  {
    "id": 154983,
    "name": "Schœlcher",
    "state_id": 5398,
    "state_code": "01",
    "country_id": 138,
    "country_code": "MQ",
    "latitude": "14.65179970",
    "longitude": "-61.14128670",
    "native": "Schœlcher",
    "timezone": "America/Caracas",
    "translations": {
      "br": "Schœlcher",
      "ko": "숄셰르",
      "pt-BR": "Schoelcher",
      "pt": "Schoelcher",
      "nl": "Schœlcher",
      "hr": "Schœlcher",
      "fa": "شولشر",
      "de": "Schœlcher",
      "es": "Schoelcher",
      "fr": "Schœlcher",
      "ja": "シェルチャー",
      "it": "Schœlcher",
      "zh-CN": "舍尔谢尔",
      "tr": "Okul",
      "ru": "Шельхер",
      "uk": "Шельхер",
      "pl": "Schœlcher",
      "hi": "Schoelcher",
      "ar": "شولشر"
    },
    "created_at": "2025-03-29T15:49:53",
    "updated_at": "2025-10-13T13:38:21",
    "flag": 1,
    "wikiDataId": "Q617806"
  },
  {
    "id": 154984,
    "name": "L'Ajoupa-Bouillon",
    "state_id": 5399,
    "state_code": "02",
    "country_id": 138,
    "country_code": "MQ",
    "latitude": "14.81597180",
    "longitude": "-61.17170630",
    "native": "L'Ajoupa-Bouillon",
    "timezone": "America/Caracas",
    "translations": {
      "br": "L'Ajoupa-Bouillon",
      "ko": "라주파-부용",
      "pt-BR": "Caldo de Ajoupa",
      "pt": "Caldo de Ajoupa",
      "nl": "L'Ajoupa-Bouillon",
      "hr": "L'Ajoupa-Bouillon",
      "fa": "لاژوپا-بویون",
      "de": "L'Ajoupa-Bouillon",
      "es": "L'Ajoupa-Bouillon",
      "fr": "L'Ajoupa-Bouillon",
      "ja": "ラジュパ・ブイヨン",
      "it": "L'Ajoupa-Bouillon",
      "zh-CN": "拉茹帕-布永",
      "tr": "L'Ajoupa-Bulyon",
      "ru": "Л'Ажупа-Буйон",
      "uk": "Л'Ажупа-Буйон",
      "pl": "L'Ajoupa-Bouillon",
      "hi": "एल'अजोपा-बौइलन",
      "ar": "لاجوبا بويون"
    },
    "created_at": "2025-03-29T15:55:03",
    "updated_at": "2025-10-13T13:38:21",
    "flag": 1,
    "wikiDataId": "Q1234080"
  },
  {
    "id": 154985,
    "name": "Basse-Pointe",
    "state_id": 5399,
    "state_code": "02",
    "country_id": 138,
    "country_code": "MQ",
    "latitude": "14.84097080",
    "longitude": "-61.16485230",
    "native": "Basse-Pointe",
    "timezone": "America/Caracas",
    "translations": {
      "br": "Basse-Pointe",
      "ko": "바스 푸앵트",
      "pt-BR": "Basse-Pointe",
      "pt": "Basse-Pointe",
      "nl": "Basse-Pointe",
      "hr": "Basse-Pointe",
      "fa": "باس-پوینت",
      "de": "Basse-Pointe",
      "es": "Punta baja",
      "fr": "Basse-Pointe",
      "ja": "バス・ポイント",
      "it": "Basse-Pointe",
      "zh-CN": "巴塞角",
      "tr": "Basse-Pointe",
      "ru": "Бас-Пуэнт",
      "uk": "Бас-Пуент",
      "pl": "Basse-Pointe",
      "hi": "बासे-पॉइंट",
      "ar": "باس بوانت"
    },
    "created_at": "2025-03-29T15:55:03",
    "updated_at": "2025-10-13T13:38:21",
    "flag": 1,
    "wikiDataId": "Q1648481"
  },
  {
    "id": 154986,
    "name": "Grand'Rivière",
    "state_id": 5399,
    "state_code": "02",
    "country_id": 138,
    "country_code": "MQ",
    "latitude": "14.84696630",
    "longitude": "-61.20427640",
    "native": "Grand'Rivière",
    "timezone": "America/Caracas",
    "translations": {
      "br": "Stêr Veur",
      "ko": "그랑리비에르",
      "pt-BR": "Grande Rio",
      "pt": "Grande Rio",
      "nl": "Grand'Rivière",
      "hr": "Grand'Rivière",
      "fa": "گراند ریویر",
      "de": "Grand'Rivière",
      "es": "Grand'Rivière",
      "fr": "Grand'Rivière",
      "ja": "グランドリヴィエール",
      "it": "Grand'Rivière",
      "zh-CN": "大里维埃",
      "tr": "Grand'Rivière",
      "ru": "Гранд-Ривьер",
      "uk": "Гранд'Рів'єр",
      "pl": "Grand'Rivière",
      "hi": "ग्रैंड'रिविएर",
      "ar": "جراند ريفيير"
    },
    "created_at": "2025-03-29T15:55:03",
    "updated_at": "2025-10-13T13:38:21",
    "flag": 1,
    "wikiDataId": "Q1650045"
  },
  {
    "id": 154987,
    "name": "Gros-Morne",
    "state_id": 5399,
    "state_code": "02",
    "country_id": 138,
    "country_code": "MQ",
    "latitude": "14.70841840",
    "longitude": "-61.11271220",
    "native": "Mameau brutal",
    "timezone": "America/Caracas",
    "translations": {
      "br": "Gros-Morne",
      "ko": "그로스-모른",
      "pt-BR": "Gros-Morne",
      "pt": "Gros-Morne",
      "nl": "Gros-Morne",
      "hr": "Gros-Morne",
      "fa": "گروس-مورن",
      "de": "Gros-Morne",
      "es": "Gros-Morne",
      "fr": "Gros-Morne",
      "ja": "グロス・モーン",
      "it": "Gros-Morne",
      "zh-CN": "格罗莫讷",
      "tr": "Gros-Morne",
      "ru": "Грос-Морн",
      "uk": "Грос-Морн",
      "pl": "Gros-Morne",
      "hi": "ग्रोस-मोर्ने",
      "ar": "جروس مورن"
    },
    "created_at": "2025-03-29T15:55:03",
    "updated_at": "2025-10-13T13:38:21",
    "flag": 1,
    "wikiDataId": "Q1778192"
  },
  {
    "id": 154988,
    "name": "Le Lorrain",
    "state_id": 5399,
    "state_code": "02",
    "country_id": 138,
    "country_code": "MQ",
    "latitude": "14.79952560",
    "longitude": "-61.11513740",
    "native": "Le Lorrain",
    "timezone": "America/Caracas",
    "translations": {
      "br": "Al Loren",
      "ko": "르 로랭",
      "pt-BR": "Le Lorrain",
      "pt": "Le Lorrain",
      "nl": "De Lorrain",
      "hr": "Le Lorrain",
      "fa": "لو لورین",
      "de": "Le Lorrain",
      "es": "Le Lorrain",
      "fr": "Le Lorrain",
      "ja": "ル・ロラン",
      "it": "Le Lorrain",
      "zh-CN": "勒洛兰",
      "tr": "Le Lorrain",
      "ru": "Ле Лоррен",
      "uk": "Ле Лоррен",
      "pl": "Lotaryngia",
      "hi": "ले लोरेन",
      "ar": "لورين"
    },
    "created_at": "2025-03-29T15:55:03",
    "updated_at": "2025-10-13T13:38:21",
    "flag": 1,
    "wikiDataId": "Q595351"
  },
  {
    "id": 154989,
    "name": "Macouba",
    "state_id": 5399,
    "state_code": "02",
    "country_id": 138,
    "country_code": "MQ",
    "latitude": "14.84743860",
    "longitude": "-61.16709460",
    "native": "Macouba",
    "timezone": "America/Caracas",
    "translations": {
      "br": "Macouba",
      "ko": "마쿠바",
      "pt-BR": "Macouba",
      "pt": "Macouba",
      "nl": "Macouba",
      "hr": "Macouba",
      "fa": "ماکوبا",
      "de": "Macouba",
      "es": "Macouba",
      "fr": "Macouba",
      "ja": "マクバ",
      "it": "Macouba",
      "zh-CN": "马库巴",
      "tr": "Macouba",
      "ru": "Макуба",
      "uk": "Макуба",
      "pl": "Macouba",
      "hi": "मकोबा",
      "ar": "ماكوبا"
    },
    "created_at": "2025-03-29T15:55:03",
    "updated_at": "2025-10-13T13:38:21",
    "flag": 1,
    "wikiDataId": "Q545210"
  },
  {
    "id": 154990,
    "name": "Le Marigot",
    "state_id": 5399,
    "state_code": "02",
    "country_id": 138,
    "country_code": "MQ",
    "latitude": "14.77958180",
    "longitude": "-61.09424580",
    "native": "Le Marigot",
    "timezone": "America/Caracas",
    "translations": {
      "br": "Ar Marigot",
      "ko": "르 마리고",
      "pt-BR": "Le Marigot",
      "pt": "Le Marigot",
      "nl": "De Marigot",
      "hr": "Le Marigot",
      "fa": "لو ماریگو",
      "de": "Le Marigot",
      "es": "Le Marigot",
      "fr": "Le Marigot",
      "ja": "ル・マリゴ",
      "it": "Le Marigot",
      "zh-CN": "勒马里戈特",
      "tr": "Le Marigot",
      "ru": "Ле Мариго",
      "uk": "Ле Маріго",
      "pl": "Le Marigot",
      "hi": "ले मैरीगोट",
      "ar": "لو ماريجوت"
    },
    "created_at": "2025-03-29T15:55:03",
    "updated_at": "2025-10-13T13:38:21",
    "flag": 1,
    "wikiDataId": "Q1778234"
  },
  {
    "id": 154991,
    "name": "Le Robert",
    "state_id": 5399,
    "state_code": "02",
    "country_id": 138,
    "country_code": "MQ",
    "latitude": "14.67443270",
    "longitude": "-61.01692720",
    "native": "Le Robert",
    "timezone": "America/Caracas",
    "translations": {
      "br": "Le Robert",
      "ko": "르 로베르",
      "pt-BR": "O Roberto",
      "pt": "O Roberto",
      "nl": "De Robert",
      "hr": "Le Robert",
      "fa": "لو رابرت",
      "de": "Le Robert",
      "es": "Le Robert",
      "fr": "Le Robert",
      "ja": "ル・ロバート",
      "it": "Le Robert",
      "zh-CN": "勒罗伯特",
      "tr": "Le Robert",
      "ru": "Ле Роберт",
      "uk": "Ле Роберт",
      "pl": "Robert",
      "hi": "ले रॉबर्ट",
      "ar": "لو روبرت"
    },
    "created_at": "2025-03-29T15:55:03",
    "updated_at": "2025-10-13T13:38:21",
    "flag": 1,
    "wikiDataId": "Q1617674"
  },
  {
    "id": 154992,
    "name": "Sainte-Marie",
    "state_id": 5399,
    "state_code": "02",
    "country_id": 138,
    "country_code": "MQ",
    "latitude": "14.77300930",
    "longitude": "-61.04959970",
    "native": "Sainte-Marie",
    "timezone": "America/Caracas",
    "translations": {
      "br": "Santez-Varia",
      "ko": "생트마리",
      "pt-BR": "Santa Maria",
      "pt": "Santa Maria",
      "nl": "Sint-Marie",
      "hr": "Sainte-Marie",
      "fa": "سنت ماری",
      "de": "Sainte-Marie",
      "es": "Santa María",
      "fr": "Sainte-Marie",
      "ja": "サントマリー",
      "it": "Santa Maria",
      "zh-CN": "圣玛丽",
      "tr": "Sainte-Marie",
      "ru": "Сент-Мари",
      "uk": "Сент-Марі",
      "pl": "Święta Maria",
      "hi": "सैंटे-मैरी",
      "ar": "سانت ماري"
    },
    "created_at": "2025-03-29T15:55:03",
    "updated_at": "2025-10-13T13:38:21",
    "flag": 1,
    "wikiDataId": "Q1758414"
  },
  {
    "id": 154993,
    "name": "La Trinité",
    "state_id": 5399,
    "state_code": "02",
    "country_id": 138,
    "country_code": "MQ",
    "latitude": "14.73804150",
    "longitude": "-61.02929560",
    "native": "La Trinité",
    "timezone": "America/Caracas",
    "translations": {
      "br": "La Trinité",
      "ko": "라 트리니테",
      "pt-BR": "A Trindade",
      "pt": "A Trindade",
      "nl": "De Drie-eenheid",
      "hr": "La Trinité",
      "fa": "لا ترینیته",
      "de": "La Trinité",
      "es": "La Trinidad",
      "fr": "La Trinité",
      "ja": "ラ・トリニテ",
      "it": "La Trinité",
      "zh-CN": "三位一体",
      "tr": "La Trinité",
      "ru": "La Trinité",
      "uk": "Ла Трініте",
      "pl": "Trójca Święta",
      "hi": "ला ट्रिनिटे",
      "ar": "الثالوث"
    },
    "created_at": "2025-03-29T15:55:03",
    "updated_at": "2025-10-13T13:38:21",
    "flag": 1,
    "wikiDataId": "Q671787"
  },
  {
    "id": 154994,
    "name": "Les Anses-d'Arlet",
    "state_id": 5400,
    "state_code": "03",
    "country_id": 138,
    "country_code": "MQ",
    "latitude": "14.49954780",
    "longitude": "-61.11481620",
    "native": "L'ANSES-D'Arlet",
    "timezone": "America/Caracas",
    "translations": {
      "br": "Les Anses-d'Arlet",
      "ko": "레 장세스-다를레",
      "pt-BR": "Les Anses-d'Arlet",
      "pt": "Les Anses-d'Arlet",
      "nl": "Les Anses-d'Arlet",
      "hr": "Les Anses-d'Arlet",
      "fa": "لس آنس-دارله",
      "de": "Les Anses-d'Arlet",
      "es": "Les Anses-d'Arlet",
      "fr": "Les Anses-d'Arlet",
      "ja": "レ・ザンス・ダルレ",
      "it": "Les Anses-d'Arlet",
      "zh-CN": "莱安斯达尔莱",
      "tr": "Les Anses-d'Arlet",
      "ru": "Les Anses-d'Arlet",
      "uk": "Лез-Анс-д'Арле",
      "pl": "Les Anses-d'Arlet",
      "hi": "लेस एन्सेस-डी'आर्लेट",
      "ar": "ليه أنسيس دارليه"
    },
    "created_at": "2025-03-29T16:05:42",
    "updated_at": "2025-10-13T13:38:21",
    "flag": 1,
    "wikiDataId": "Q1928126"
  },
  {
    "id": 154995,
    "name": "Le Diamant",
    "state_id": 5400,
    "state_code": "03",
    "country_id": 138,
    "country_code": "MQ",
    "latitude": "14.47680040",
    "longitude": "-61.05973840",
    "native": "Le Diamant",
    "timezone": "America/Caracas",
    "translations": {
      "br": "Le Diamant",
      "ko": "르 디아망",
      "pt-BR": "O Diamante",
      "pt": "O Diamante",
      "nl": "De Diamant",
      "hr": "Le Diamant",
      "fa": "لو دیامانت",
      "de": "Le Diamant",
      "es": "El diamante",
      "fr": "Le Diamant",
      "ja": "ル・ディアマン",
      "it": "Il Diamante",
      "zh-CN": "钻石",
      "tr": "Le Diamant",
      "ru": "Ле Диамант",
      "uk": "Ле Діамант",
      "pl": "Diament",
      "hi": "ले डायमंड",
      "ar": "لو ديامانت"
    },
    "created_at": "2025-03-29T16:06:37",
    "updated_at": "2025-10-13T13:38:21",
    "flag": 1,
    "wikiDataId": "Q1928084"
  },
  {
    "id": 154996,
    "name": "Ducos",
    "state_id": 5400,
    "state_code": "03",
    "country_id": 138,
    "country_code": "MQ",
    "latitude": "14.57854420",
    "longitude": "-61.00973860",
    "native": "Ducos",
    "timezone": "America/Caracas",
    "translations": {
      "br": "Ducos",
      "ko": "두코스",
      "pt-BR": "Ducos",
      "pt": "Ducos",
      "nl": "Ducos",
      "hr": "Ducos",
      "fa": "دوکوس",
      "de": "Ducos",
      "es": "Ducos",
      "fr": "Ducos",
      "ja": "デュコス",
      "it": "Ducos",
      "zh-CN": "杜科斯",
      "tr": "Ducos",
      "ru": "Дюко",
      "uk": "Дюкос",
      "pl": "Ducos",
      "hi": "ड्यूकोस",
      "ar": "دوكوس"
    },
    "created_at": "2025-03-29T16:06:37",
    "updated_at": "2025-10-13T13:38:21",
    "flag": 1,
    "wikiDataId": "Q1928113"
  },
  {
    "id": 154997,
    "name": "Le François",
    "state_id": 5400,
    "state_code": "03",
    "country_id": 138,
    "country_code": "MQ",
    "latitude": "14.60928850",
    "longitude": "-60.97999110",
    "native": "Le François",
    "timezone": "America/Caracas",
    "translations": {
      "br": "Ar Frañsez",
      "ko": "르 프랑수아",
      "pt-BR": "Le François",
      "pt": "Le François",
      "nl": "De François",
      "hr": "Le François",
      "fa": "لو فرانسوا",
      "de": "Le François",
      "es": "El François",
      "fr": "Le François",
      "ja": "ル・フランソワ",
      "it": "Le François",
      "zh-CN": "弗朗索瓦",
      "tr": "Le François",
      "ru": "Ле Франсуа",
      "uk": "Ле Франсуа",
      "pl": "Le François",
      "hi": "ले फ़्राँस्वा",
      "ar": "لو فرانسوا"
    },
    "created_at": "2025-03-29T16:06:37",
    "updated_at": "2025-10-13T13:38:21",
    "flag": 1,
    "wikiDataId": "Q282944"
  },
  {
    "id": 154998,
    "name": "Le Marin",
    "state_id": 5400,
    "state_code": "03",
    "country_id": 138,
    "country_code": "MQ",
    "latitude": "14.48221690",
    "longitude": "-60.90011410",
    "native": "Le Marin",
    "timezone": "America/Caracas",
    "translations": {
      "br": "Le Marin",
      "ko": "르 마린",
      "pt-BR": "Le Marin",
      "pt": "Le Marin",
      "nl": "De zeeman",
      "hr": "Le Marin",
      "fa": "لو مارین",
      "de": "Le Marin",
      "es": "Le Marin",
      "fr": "Le Marin",
      "ja": "ル・マリン",
      "it": "Le Marin",
      "zh-CN": "勒马林",
      "tr": "Le Marin",
      "ru": "Ле Марин",
      "uk": "Ле Марін",
      "pl": "Le Marin",
      "hi": "ले मारिन",
      "ar": "لو مارين"
    },
    "created_at": "2025-03-29T16:06:37",
    "updated_at": "2025-10-13T13:38:21",
    "flag": 1,
    "wikiDataId": "Q265373"
  },
  {
    "id": 154999,
    "name": "Rivière-Pilote",
    "state_id": 5400,
    "state_code": "03",
    "country_id": 138,
    "country_code": "MQ",
    "latitude": "14.50266970",
    "longitude": "-60.93819210",
    "native": "Rivière-Pilote",
    "timezone": "America/Caracas",
    "translations": {
      "br": "Rivière-Pilote",
      "ko": "리비에르-필로트",
      "pt-BR": "Rivière-Pilote",
      "pt": "Rivière-Pilote",
      "nl": "Rivier-Pilote",
      "hr": "Rivière-Pilote",
      "fa": "ریویر-پیلوت",
      "de": "Rivière-Pilote",
      "es": "Río Pilote",
      "fr": "Rivière-Pilote",
      "ja": "リヴィエール・ピロテ",
      "it": "Rivière-Pilote",
      "zh-CN": "里维埃-皮洛特",
      "tr": "Rivière-Pilote",
      "ru": "Ривьер-Пилот",
      "uk": "Рів'єр-Пілот",
      "pl": "Rivière-Pilote",
      "hi": "रिविएर-पायलट",
      "ar": "ريفيير بيلوت"
    },
    "created_at": "2025-03-29T16:06:37",
    "updated_at": "2025-10-13T13:38:21",
    "flag": 1,
    "wikiDataId": "Q1918091"
  },
  {
    "id": 155000,
    "name": "Rivière-Salée",
    "state_id": 5400,
    "state_code": "03",
    "country_id": 138,
    "country_code": "MQ",
    "latitude": "14.52621400",
    "longitude": "-61.00353090",
    "native": "Rivière-Salée",
    "timezone": "America/Caracas",
    "translations": {
      "br": "Rivière-Salée",
      "ko": "리비에르-살레",
      "pt-BR": "Rivière-Salée",
      "pt": "Rivière-Salée",
      "nl": "Rivier-Salée",
      "hr": "Rivière-Salée",
      "fa": "ریویر-سالی",
      "de": "Rivière-Salée",
      "es": "Rivière-Salée",
      "fr": "Rivière-Salée",
      "ja": "リヴィエール・サレ",
      "it": "Rivière-Salée",
      "zh-CN": "里维埃-萨莱",
      "tr": "Rivière-Salée",
      "ru": "Ривьер-Сале",
      "uk": "Рів'єр-Сале",
      "pl": "Rivière-Salée",
      "hi": "Rivière-Salee",
      "ar": "ريفيير سالي"
    },
    "created_at": "2025-03-29T16:06:37",
    "updated_at": "2025-10-13T13:38:21",
    "flag": 1,
    "wikiDataId": "Q1928099"
  },
  {
    "id": 155001,
    "name": "Saint-Esprit",
    "state_id": 5400,
    "state_code": "03",
    "country_id": 138,
    "country_code": "MQ",
    "latitude": "14.56175950",
    "longitude": "-60.96451110",
    "native": "Saint-Esprit",
    "timezone": "America/Caracas",
    "translations": {
      "br": "Sant-Esper",
      "ko": "생트-에스프리",
      "pt-BR": "Santo Espírito",
      "pt": "Santo Espírito",
      "nl": "Sint-Esprit",
      "hr": "Saint-Esprit",
      "fa": "سنت اسپری",
      "de": "Saint-Esprit",
      "es": "Santo Espíritu",
      "fr": "Saint-Esprit",
      "ja": "サン・テスプリ",
      "it": "Santo Spirito",
      "zh-CN": "圣埃斯普里特",
      "tr": "Aziz-Esprit",
      "ru": "Сент-Эспри",
      "uk": "Сен-Еспрі",
      "pl": "Święty-Esprit",
      "hi": "सेंट एस्प्रिट",
      "ar": "سانت إسبريت"
    },
    "created_at": "2025-03-29T16:06:37",
    "updated_at": "2025-10-13T13:38:21",
    "flag": 1,
    "wikiDataId": "Q1928039"
  },
  {
    "id": 155002,
    "name": "Sainte-Anne",
    "state_id": 5400,
    "state_code": "03",
    "country_id": 138,
    "country_code": "MQ",
    "latitude": "14.43142200",
    "longitude": "-60.89278760",
    "native": "Sainte-Anne",
    "timezone": "America/Caracas",
    "translations": {
      "br": "Santez-Anna",
      "ko": "생트앤",
      "pt-BR": "Santa Ana",
      "pt": "Santa Ana",
      "nl": "Sint-Anna",
      "hr": "Sainte-Anne",
      "fa": "سنت-آن",
      "de": "Sainte-Anne",
      "es": "Santa Ana",
      "fr": "Sainte-Anne",
      "ja": "サンタンヌ",
      "it": "Sant'Anna",
      "zh-CN": "圣安妮",
      "tr": "Sainte-Anne",
      "ru": "Сент-Анн",
      "uk": "Сент-Анн",
      "pl": "Święta Anna",
      "hi": "सैंटे-ऐनी",
      "ar": "سانت آن"
    },
    "created_at": "2025-03-29T16:06:37",
    "updated_at": "2025-10-13T13:38:21",
    "flag": 1,
    "wikiDataId": "Q655146"
  },
  {
    "id": 155003,
    "name": "Sainte-Luce",
    "state_id": 5400,
    "state_code": "03",
    "country_id": 138,
    "country_code": "MQ",
    "latitude": "14.49040930",
    "longitude": "-60.98793650",
    "native": "Sainte-Luce",
    "timezone": "America/Caracas",
    "translations": {
      "br": "Santez-Lus",
      "ko": "생트루스",
      "pt-BR": "Santa Luzia",
      "pt": "Santa Luzia",
      "nl": "Sainte-Luce",
      "hr": "Sainte-Luce",
      "fa": "سنت-لوس",
      "de": "Sainte-Luce",
      "es": "Santa Lucía",
      "fr": "Sainte-Luce",
      "ja": "サント・リュス",
      "it": "Santa Luce",
      "zh-CN": "圣吕斯",
      "tr": "Sainte-Luce",
      "ru": "Сент-Люс",
      "uk": "Сент-Люс",
      "pl": "Sainte-Luce",
      "hi": "Sainte-लूस",
      "ar": "سانت لوسي"
    },
    "created_at": "2025-03-29T16:06:37",
    "updated_at": "2025-10-13T13:38:21",
    "flag": 1,
    "wikiDataId": "Q1772486"
  },
  {
    "id": 155004,
    "name": "Les Trois-Îlets",
    "state_id": 5400,
    "state_code": "03",
    "country_id": 138,
    "country_code": "MQ",
    "latitude": "14.53287460",
    "longitude": "-61.07877690",
    "native": "Les Trois-Îlets",
    "timezone": "America/Caracas",
    "translations": {
      "br": "An Trois-Enez",
      "ko": "레 트루아-일레",
      "pt-BR": "Les Trois-Îlets",
      "pt": "Les Trois-Îlets",
      "nl": "Les Trois-Îlets",
      "hr": "Les Trois-Îlets",
      "fa": "سه جزیره",
      "de": "Les Trois-Îlets",
      "es": "Las Tres Îletas",
      "fr": "Les Trois-Îlets",
      "ja": "レ・トロワ・イレ",
      "it": "Les Trois-Îlets",
      "zh-CN": "莱特鲁瓦西莱",
      "tr": "Üçlüler",
      "ru": "Les Trois-Îlets",
      "uk": "Ле-Труа-Іле",
      "pl": "Les Trois-Îlets",
      "hi": "लेस ट्रोइस-इलेट्स",
      "ar": "الجزر الثلاث"
    },
    "created_at": "2025-03-29T16:06:37",
    "updated_at": "2025-10-13T13:38:21",
    "flag": 1,
    "wikiDataId": "Q1650786"
  },
  {
    "id": 155005,
    "name": "Le Vauclin",
    "state_id": 5400,
    "state_code": "03",
    "country_id": 138,
    "country_code": "MQ",
    "latitude": "14.54208600",
    "longitude": "-60.90060060",
    "native": "Le Vauclin",
    "timezone": "America/Caracas",
    "translations": {
      "br": "Ar Vauclin",
      "ko": "르 보클린",
      "pt-BR": "Le Vauclin",
      "pt": "Le Vauclin",
      "nl": "De Vauclin",
      "hr": "Le Vauclin",
      "fa": "لو ووکلین",
      "de": "Le Vauclin",
      "es": "Le Vauclin",
      "fr": "Le Vauclin",
      "ja": "ル・ヴォークラン",
      "it": "Le Vauclin",
      "zh-CN": "勒沃克兰",
      "tr": "Le Vauclin",
      "ru": "Ле Воклен",
      "uk": "Ле Воклен",
      "pl": "Le Vauclin",
      "hi": "ले वौक्लिन",
      "ar": "لو فوكلين"
    },
    "created_at": "2025-03-29T16:06:37",
    "updated_at": "2025-10-13T13:38:21",
    "flag": 1,
    "wikiDataId": "Q1831094"
  },
  {
    "id": 155006,
    "name": "Bellefontaine",
    "state_id": 5401,
    "state_code": "04",
    "country_id": 138,
    "country_code": "MQ",
    "latitude": "14.67474760",
    "longitude": "-61.16653080",
    "native": "Bellefontaine",
    "timezone": "America/Caracas",
    "translations": {
      "br": "Bellefontaine",
      "ko": "벨폰테인",
      "pt-BR": "Bellefontaine",
      "pt": "Bellefontaine",
      "nl": "Bellefontaine",
      "hr": "Bellefontaine",
      "fa": "بلفونتین",
      "de": "Bellefontaine",
      "es": "Bellefontaine",
      "fr": "Bellefontaine",
      "ja": "ベルフォンテーヌ",
      "it": "Bellefontaine",
      "zh-CN": "贝尔方丹",
      "tr": "Bellefontaine",
      "ru": "Белльфонтен",
      "uk": "Бельфонтен",
      "pl": "Bellefontaine",
      "hi": "बेलेफोंटेन",
      "ar": "بيلفونتين"
    },
    "created_at": "2025-03-29T16:16:49",
    "updated_at": "2025-10-13T13:38:21",
    "flag": 1,
    "wikiDataId": "Q1778187"
  },
  {
    "id": 155007,
    "name": "Le Carbet",
    "state_id": 5401,
    "state_code": "04",
    "country_id": 138,
    "country_code": "MQ",
    "latitude": "14.70521580",
    "longitude": "-61.19444680",
    "native": "Le Carbet",
    "timezone": "America/Caracas",
    "translations": {
      "br": "Le Carbet",
      "ko": "르 카르베",
      "pt-BR": "Le Carbet",
      "pt": "Le Carbet",
      "nl": "Le Carbet",
      "hr": "Le Carbet",
      "fa": "لو کاربت",
      "de": "Le Carbet",
      "es": "El Carbet",
      "fr": "Le Carbet",
      "ja": "ル・カルベ",
      "it": "Le Carbet",
      "zh-CN": "勒卡尔贝",
      "tr": "Le Carbet",
      "ru": "Ле Карбе",
      "uk": "Ле Карбе",
      "pl": "Le Carbet",
      "hi": "ले कार्बेट",
      "ar": "لو كاربيت"
    },
    "created_at": "2025-03-29T16:16:49",
    "updated_at": "2025-10-13T13:38:21",
    "flag": 1,
    "wikiDataId": "Q747519"
  },
  {
    "id": 155008,
    "name": "Case-Pilote",
    "state_id": 5401,
    "state_code": "04",
    "country_id": 138,
    "country_code": "MQ",
    "latitude": "14.65933990",
    "longitude": "-61.15026120",
    "native": "Case-Pilote",
    "timezone": "America/Caracas",
    "translations": {
      "br": "Case-Pilote",
      "ko": "케이스-필로테",
      "pt-BR": "Caso-Piloto",
      "pt": "Caso-Piloto",
      "nl": "Case-Pilot",
      "hr": "Case-Pilot",
      "fa": "کیس-پایلوت",
      "de": "Case-Pilote",
      "es": "Caso Piloto",
      "fr": "Cas-Pilote",
      "ja": "ケースパイロット",
      "it": "Caso-Pilota",
      "zh-CN": "案例飞行员",
      "tr": "Case-Pilote",
      "ru": "Кейс-пилот",
      "uk": "Кейс-пілот",
      "pl": "Case-Pilote",
      "hi": "केस-Pilote",
      "ar": "كيس-بيلوت"
    },
    "created_at": "2025-03-29T16:16:49",
    "updated_at": "2025-10-13T13:38:21",
    "flag": 1,
    "wikiDataId": "Q1928049"
  },
  {
    "id": 155009,
    "name": "Fonds-Saint-Denis",
    "state_id": 5401,
    "state_code": "04",
    "country_id": 138,
    "country_code": "MQ",
    "latitude": "14.72275460",
    "longitude": "-61.16189190",
    "native": "Fonds-Saint-Denis",
    "timezone": "America/Caracas",
    "translations": {
      "br": "Fonds-Saint-Denis",
      "ko": "퐁생드니",
      "pt-BR": "Fundo Saint-Denis",
      "pt": "Fundo Saint-Denis",
      "nl": "Fonds-Saint-Denis",
      "hr": "Fonds-Saint-Denis",
      "fa": "فوندز-سن-دنی",
      "de": "Fonds-Saint-Denis",
      "es": "Fondo Saint-Denis",
      "fr": "Fonds-Saint-Denis",
      "ja": "フォン・サン・ドニ",
      "it": "Fonds-Saint-Denis",
      "zh-CN": "圣丹尼斯基金会",
      "tr": "Fonds-Saint-Denis",
      "ru": "Фон-Сен-Дени",
      "uk": "Фон-Сен-Дені",
      "pl": "Fundusz Saint-Denis",
      "hi": "फोंड्स-सेंट-डेनिस",
      "ar": "فوندز-سانت-ديني"
    },
    "created_at": "2025-03-29T16:16:49",
    "updated_at": "2025-10-13T13:38:21",
    "flag": 1,
    "wikiDataId": "Q1928060"
  },
  {
    "id": 155010,
    "name": "Le Morne-Rouge",
    "state_id": 5401,
    "state_code": "04",
    "country_id": 138,
    "country_code": "MQ",
    "latitude": "14.76953640",
    "longitude": "-61.16292840",
    "native": "Le Morne-Rouge",
    "timezone": "America/Caracas",
    "translations": {
      "br": "Le Morne-Rouge",
      "ko": "르 모르네-루즈",
      "pt-BR": "Le Morne-Rouge",
      "pt": "Le Morne-Rouge",
      "nl": "Le Morne-Rouge",
      "hr": "Le Morne-Rouge",
      "fa": "لو مورن-روژ",
      "de": "Le Morne-Rouge",
      "es": "El Morne-Rouge",
      "fr": "Le Morne-Rouge",
      "ja": "ル・モーン・ルージュ",
      "it": "Le Morne-Rouge",
      "zh-CN": "勒莫讷-鲁日",
      "tr": "Le Morne-Rouge",
      "ru": "Ле Морн-Руж",
      "uk": "Ле-Морн-Руж",
      "pl": "Le Morne-Rouge",
      "hi": "ले मोर्ने-रूज",
      "ar": "لو مورن روج"
    },
    "created_at": "2025-03-29T16:16:49",
    "updated_at": "2025-10-13T13:38:21",
    "flag": 1,
    "wikiDataId": "Q974759"
  },
  {
    "id": 155011,
    "name": "Le Morne-Vert",
    "state_id": 5401,
    "state_code": "04",
    "country_id": 138,
    "country_code": "MQ",
    "latitude": "14.70464330",
    "longitude": "-61.15679770",
    "native": "Le Morne-Vert",
    "timezone": "America/Caracas",
    "translations": {
      "br": "Le Morne-Vert",
      "ko": "르 모르네-베르",
      "pt-BR": "Le Morne-Vert",
      "pt": "Le Morne-Vert",
      "nl": "Le Morne-Vert",
      "hr": "Le Morne-Vert",
      "fa": "لو مورن-ورت",
      "de": "Le Morne-Vert",
      "es": "El Morne-Vert",
      "fr": "Le Morne-Vert",
      "ja": "ル・モーン・ヴェール",
      "it": "Le Morne-Vert",
      "zh-CN": "勒莫讷韦尔",
      "tr": "Le Morne-Vert",
      "ru": "Ле Морн-Вер",
      "uk": "Ле-Морн-Вер",
      "pl": "Le Morne-Vert",
      "hi": "ले मोर्ने-वर्ट",
      "ar": "لو مورن فيرت"
    },
    "created_at": "2025-03-29T16:16:49",
    "updated_at": "2025-10-13T13:38:21",
    "flag": 1,
    "wikiDataId": "Q943994"
  },
  {
    "id": 155012,
    "name": "Le Prêcheur",
    "state_id": 5401,
    "state_code": "04",
    "country_id": 138,
    "country_code": "MQ",
    "latitude": "14.82202610",
    "longitude": "-61.23746860",
    "native": "Le Prêcheur",
    "timezone": "America/Caracas",
    "translations": {
      "br": "Le Prêcheur",
      "ko": "르 프레슈르",
      "pt-BR": "O Pregador",
      "pt": "O Pregador",
      "nl": "De Prêcheur",
      "hr": "Le Prêcheur",
      "fa": "لو پریشور",
      "de": "Le Prêcheur",
      "es": "El Predicador",
      "fr": "Le Prêcheur",
      "ja": "ル・プレシェール",
      "it": "Le Prêcheur",
      "zh-CN": "Le Prêcheur",
      "tr": "Le Prêcheur",
      "ru": "Проповедник",
      "uk": "Ле Прешер",
      "pl": "Prêcheur",
      "hi": "ले प्रीचेउर",
      "ar": "Le Prêcheur"
    },
    "created_at": "2025-03-29T16:16:49",
    "updated_at": "2025-10-13T13:38:21",
    "flag": 1,
    "wikiDataId": "Q1778157"
  },
  {
    "id": 155013,
    "name": "Saint-Pierre",
    "state_id": 5401,
    "state_code": "04",
    "country_id": 138,
    "country_code": "MQ",
    "latitude": "14.77167190",
    "longitude": "-61.21475010",
    "native": "Saint-Pierre",
    "timezone": "America/Caracas",
    "translations": {
      "br": "Sant-Pêr",
      "ko": "생 피에르",
      "pt-BR": "São Pedro",
      "pt": "São Pedro",
      "nl": "Sint-Pieter",
      "hr": "Saint-Pierre",
      "fa": "سن پیر",
      "de": "Saint-Pierre",
      "es": "San Pedro",
      "fr": "Saint-Pierre",
      "ja": "サンピエール",
      "it": "Saint-Pierre",
      "zh-CN": "圣皮埃尔",
      "tr": "Saint-Pierre",
      "ru": "Сен-Пьер",
      "uk": "Сен-П'єр",
      "pl": "Saint-Pierre",
      "hi": "सेंट पियरे",
      "ar": "سان بيير"
    },
    "created_at": "2025-03-29T16:16:49",
    "updated_at": "2025-10-13T13:38:21",
    "flag": 1,
    "wikiDataId": "Q589980"
  }
]